{
  "trackers": [
    {
      "type": "google fonts",
      "url": "https://fonts.googleapis.com/css?family=Source+Sans+Pro",
      "details": {
        "id": "google fonts",
        "message": "Host the font locally with https://github.com/neverpanic/google-font-download or https://google-webfonts-helper.herokuapp.com/"
      }
    },
    {
      "type": "google",
      "url": "https://ajax.googleapis.com/ajax/libs/jquery/2.1.0/jquery.min.js",
      "details": {
        "id": "google",
        "message": "Use hosted Matomo instance"
      }
    },
    {
      "type": "FontAwesome",
      "url": "https://use.fontawesome.com/releases/v5.13.1/js/all.js",
      "details": {
        "id": "FontAwesome",
        "message": "Host fonts directly"
      }
    },
    {
      "type": "FontAwesome",
      "url": "https://use.fontawesome.com/releases/v5.13.1/js/v4-shims.js",
      "details": {
        "id": "FontAwesome",
        "message": "Host fonts directly"
      }
    },
    {
      "type": "google fonts",
      "url": "https://fonts.gstatic.com/s/sourcesanspro/v21/6xK3dSBYKcSV-LCoeQqfX1RYOo3qOK7l.woff2",
      "details": {
        "id": "google fonts",
        "message": "Host the font locally with https://github.com/neverpanic/google-font-download or https://google-webfonts-helper.herokuapp.com/"
      }
    },
    {
      "type": "unknown",
      "url": "https://static.addtoany.com/menu/page.js"
    },
    {
      "type": "unknown",
      "url": "https://player.vimeo.com/video/486892019"
    },
    {
      "type": "unknown",
      "url": "https://player.vimeo.com/video/515661695"
    },
    {
      "type": "unknown",
      "url": "https://player.vimeo.com/video/649614883"
    },
    {
      "type": "unknown",
      "url": "https://player.vimeo.com/video/591490868"
    },
    {
      "type": "google fonts",
      "url": "https://fonts.gstatic.com/s/sourcesanspro/v21/6xK3dSBYKcSV-LCoeQqfX1RYOo3qOK7l.woff2",
      "details": {
        "id": "google fonts",
        "message": "Host the font locally with https://github.com/neverpanic/google-font-download or https://google-webfonts-helper.herokuapp.com/"
      }
    },
    {
      "type": "unknown",
      "url": "https://player.vimeo.com/video/577204331"
    },
    {
      "type": "unknown",
      "url": "https://player.vimeo.com/video/617739562"
    },
    {
      "type": "unknown",
      "url": "https://player.vimeo.com/video/657346945"
    },
    {
      "type": "unknown",
      "url": "https://player.vimeo.com/video/658505731"
    },
    {
      "type": "unknown",
      "url": "https://player.vimeo.com/video/658549972"
    },
    {
      "type": "unknown",
      "url": "https://player.vimeo.com/video/660618173"
    },
    {
      "type": "unknown",
      "url": "https://player.vimeo.com/video/665994111"
    },
    {
      "type": "vimeo",
      "url": "https://i.vimeocdn.com/video/1007720184-ff7f41c1d011ccdc1f065763736bf1ca12c20a58db02c8c788a0606edf5f8c56-d.jpg?mw=80&q=85",
      "details": {
        "id": "vimeo",
        "message": "use peertube"
      }
    },
    {
      "type": "vimeo",
      "url": "https://i.vimeocdn.com/video/1222770267-e0dd28785a5fa76cb373a75427aa00fdc5667a74a5aa360fd310eb9ea6fc358c-d.jpg?mw=80&q=85",
      "details": {
        "id": "vimeo",
        "message": "use peertube"
      }
    },
    {
      "type": "vimeo",
      "url": "https://f.vimeocdn.com/p/4.9.7/js/player.js",
      "details": {
        "id": "vimeo",
        "message": "use peertube"
      }
    },
    {
      "type": "vimeo",
      "url": "https://f.vimeocdn.com/p/4.9.7/css/player.css",
      "details": {
        "id": "vimeo",
        "message": "use peertube"
      }
    },
    {
      "type": "vimeo",
      "url": "https://f.vimeocdn.com/js_opt/modules/utils/vuid.min.js",
      "details": {
        "id": "vimeo",
        "message": "use peertube"
      }
    },
    {
      "type": "vimeo",
      "url": "https://i.vimeocdn.com/video/1068690231-fac2ffabd03f7ec4fca00ad3bda7d1f788ca36088728005d1242b51ba8c2c708-d.jpg?mw=80&q=85",
      "details": {
        "id": "vimeo",
        "message": "use peertube"
      }
    },
    {
      "type": "vimeo",
      "url": "https://f.vimeocdn.com/p/4.9.7/js/player.js",
      "details": {
        "id": "vimeo",
        "message": "use peertube"
      }
    },
    {
      "type": "vimeo",
      "url": "https://f.vimeocdn.com/p/4.9.7/css/player.css",
      "details": {
        "id": "vimeo",
        "message": "use peertube"
      }
    },
    {
      "type": "vimeo",
      "url": "https://f.vimeocdn.com/js_opt/modules/utils/vuid.min.js",
      "details": {
        "id": "vimeo",
        "message": "use peertube"
      }
    },
    {
      "type": "vimeo",
      "url": "https://f.vimeocdn.com/p/4.9.7/js/player.js",
      "details": {
        "id": "vimeo",
        "message": "use peertube"
      }
    },
    {
      "type": "vimeo",
      "url": "https://f.vimeocdn.com/p/4.9.7/css/player.css",
      "details": {
        "id": "vimeo",
        "message": "use peertube"
      }
    },
    {
      "type": "vimeo",
      "url": "https://f.vimeocdn.com/js_opt/modules/utils/vuid.min.js",
      "details": {
        "id": "vimeo",
        "message": "use peertube"
      }
    },
    {
      "type": "vimeo",
      "url": "https://i.vimeocdn.com/video/1194006922-0bf7f2d94e08c73c5572adc5c84613b078264d51229fa632f3540478fc399cd4-d.jpg?mw=80&q=85",
      "details": {
        "id": "vimeo",
        "message": "use peertube"
      }
    },
    {
      "type": "vimeo",
      "url": "https://f.vimeocdn.com/p/4.9.7/js/player.js",
      "details": {
        "id": "vimeo",
        "message": "use peertube"
      }
    },
    {
      "type": "vimeo",
      "url": "https://f.vimeocdn.com/p/4.9.7/css/player.css",
      "details": {
        "id": "vimeo",
        "message": "use peertube"
      }
    },
    {
      "type": "vimeo",
      "url": "https://f.vimeocdn.com/js_opt/modules/utils/vuid.min.js",
      "details": {
        "id": "vimeo",
        "message": "use peertube"
      }
    },
    {
      "type": "vimeo",
      "url": "https://i.vimeocdn.com/video/1259822965-1fb41906639b692901e934675787664da0eb9120b56533d49.jpg?mw=80&q=85",
      "details": {
        "id": "vimeo",
        "message": "use peertube"
      }
    },
    {
      "type": "vimeo",
      "url": "https://f.vimeocdn.com/p/4.9.7/js/player.js",
      "details": {
        "id": "vimeo",
        "message": "use peertube"
      }
    },
    {
      "type": "vimeo",
      "url": "https://f.vimeocdn.com/p/4.9.7/css/player.css",
      "details": {
        "id": "vimeo",
        "message": "use peertube"
      }
    },
    {
      "type": "vimeo",
      "url": "https://f.vimeocdn.com/js_opt/modules/utils/vuid.min.js",
      "details": {
        "id": "vimeo",
        "message": "use peertube"
      }
    },
    {
      "type": "vimeo",
      "url": "https://i.vimeocdn.com/video/1327083600-79df17abbbd56b8e57f78912b8c23cd84949c84b2a6e0ff9af6e02315fe7e2c9-d.jpg?mw=80&q=85",
      "details": {
        "id": "vimeo",
        "message": "use peertube"
      }
    },
    {
      "type": "vimeo",
      "url": "https://f.vimeocdn.com/p/4.9.7/js/player.js",
      "details": {
        "id": "vimeo",
        "message": "use peertube"
      }
    },
    {
      "type": "vimeo",
      "url": "https://f.vimeocdn.com/p/4.9.7/css/player.css",
      "details": {
        "id": "vimeo",
        "message": "use peertube"
      }
    },
    {
      "type": "vimeo",
      "url": "https://i.vimeocdn.com/video/1310162640-d203197fe429961d85000b729bffb695af57a92d4e7f3836c.jpg?mw=80&q=85",
      "details": {
        "id": "vimeo",
        "message": "use peertube"
      }
    },
    {
      "type": "vimeo",
      "url": "https://f.vimeocdn.com/js_opt/modules/utils/vuid.min.js",
      "details": {
        "id": "vimeo",
        "message": "use peertube"
      }
    },
    {
      "type": "vimeo",
      "url": "https://f.vimeocdn.com/p/4.9.7/js/player.js",
      "details": {
        "id": "vimeo",
        "message": "use peertube"
      }
    },
    {
      "type": "vimeo",
      "url": "https://f.vimeocdn.com/p/4.9.7/css/player.css",
      "details": {
        "id": "vimeo",
        "message": "use peertube"
      }
    },
    {
      "type": "vimeo",
      "url": "https://f.vimeocdn.com/js_opt/modules/utils/vuid.min.js",
      "details": {
        "id": "vimeo",
        "message": "use peertube"
      }
    },
    {
      "type": "vimeo",
      "url": "https://i.vimeocdn.com/video/1335310154-d53a39032b28983faa5542dff6f665aaa52baafeea9355bb3982a16eee659e6a-d.jpg?mw=80&q=85",
      "details": {
        "id": "vimeo",
        "message": "use peertube"
      }
    },
    {
      "type": "vimeo",
      "url": "https://f.vimeocdn.com/p/4.9.7/js/player.js",
      "details": {
        "id": "vimeo",
        "message": "use peertube"
      }
    },
    {
      "type": "vimeo",
      "url": "https://f.vimeocdn.com/p/4.9.7/css/player.css",
      "details": {
        "id": "vimeo",
        "message": "use peertube"
      }
    },
    {
      "type": "vimeo",
      "url": "https://f.vimeocdn.com/js_opt/modules/utils/vuid.min.js",
      "details": {
        "id": "vimeo",
        "message": "use peertube"
      }
    },
    {
      "type": "vimeo",
      "url": "https://i.vimeocdn.com/video/1329848286-b2d02a1d00f50d5abc2dfaecc0f5963d86e7a89d8bfbaf0a84793bb5aed5c37b-d.jpg?mw=80&q=85",
      "details": {
        "id": "vimeo",
        "message": "use peertube"
      }
    },
    {
      "type": "vimeo",
      "url": "https://f.vimeocdn.com/p/4.9.7/js/player.js",
      "details": {
        "id": "vimeo",
        "message": "use peertube"
      }
    },
    {
      "type": "vimeo",
      "url": "https://f.vimeocdn.com/p/4.9.7/css/player.css",
      "details": {
        "id": "vimeo",
        "message": "use peertube"
      }
    },
    {
      "type": "vimeo",
      "url": "https://f.vimeocdn.com/js_opt/modules/utils/vuid.min.js",
      "details": {
        "id": "vimeo",
        "message": "use peertube"
      }
    },
    {
      "type": "vimeo",
      "url": "https://i.vimeocdn.com/video/1329938929-85eb93d872c31bad2dbb0f73c2cf87dcb286ad37da926b2c4cfe72136f2edafd-d.jpg?mw=80&q=85",
      "details": {
        "id": "vimeo",
        "message": "use peertube"
      }
    },
    {
      "type": "vimeo",
      "url": "https://f.vimeocdn.com/p/4.9.7/js/player.js",
      "details": {
        "id": "vimeo",
        "message": "use peertube"
      }
    },
    {
      "type": "vimeo",
      "url": "https://f.vimeocdn.com/p/4.9.7/css/player.css",
      "details": {
        "id": "vimeo",
        "message": "use peertube"
      }
    },
    {
      "type": "vimeo",
      "url": "https://f.vimeocdn.com/js_opt/modules/utils/vuid.min.js",
      "details": {
        "id": "vimeo",
        "message": "use peertube"
      }
    },
    {
      "type": "vimeo",
      "url": "https://i.vimeocdn.com/video/1348075437-ea38fd38163c7b66d9c364fff4c97581fa71914a5a4dd2cbd4592404e3afee86-d.jpg?mw=80&q=85",
      "details": {
        "id": "vimeo",
        "message": "use peertube"
      }
    },
    {
      "type": "vimeo",
      "url": "https://f.vimeocdn.com/p/4.9.7/js/player.js",
      "details": {
        "id": "vimeo",
        "message": "use peertube"
      }
    },
    {
      "type": "vimeo",
      "url": "https://f.vimeocdn.com/p/4.9.7/css/player.css",
      "details": {
        "id": "vimeo",
        "message": "use peertube"
      }
    },
    {
      "type": "vimeo",
      "url": "https://f.vimeocdn.com/js_opt/modules/utils/vuid.min.js",
      "details": {
        "id": "vimeo",
        "message": "use peertube"
      }
    },
    {
      "type": "unknown",
      "url": "https://static.addtoany.com/menu/modules/core.e18d3993.js"
    },
    {
      "type": "unknown",
      "url": "https://vimeo.com/ablincoln/vuid?pid=4a2e6a12fe8c7f5dee9d40c091cd968c1f0157ad1662274103"
    },
    {
      "type": "vimeo",
      "url": "https://fresnel.vimeocdn.com/add/player-test-impression?beacon=1",
      "details": {
        "id": "vimeo",
        "message": "use peertube"
      }
    },
    {
      "type": "vimeo",
      "url": "https://i.vimeocdn.com/video/1007720184-ff7f41c1d011ccdc1f065763736bf1ca12c20a58db02c8c788a0606edf5f8c56-d?mw=800&mh=451",
      "details": {
        "id": "vimeo",
        "message": "use peertube"
      }
    },
    {
      "type": "vimeo",
      "url": "https://fresnel.vimeocdn.com/add/player-stats?beacon=1&session-id=4a2e6a12fe8c7f5dee9d40c091cd968c1f0157ad1662274103",
      "details": {
        "id": "vimeo",
        "message": "use peertube"
      }
    },
    {
      "type": "vimeo",
      "url": "https://fresnel.vimeocdn.com/add/player-test-impression?beacon=1",
      "details": {
        "id": "vimeo",
        "message": "use peertube"
      }
    },
    {
      "type": "vimeo",
      "url": "https://i.vimeocdn.com/video/1222770267-e0dd28785a5fa76cb373a75427aa00fdc5667a74a5aa360fd310eb9ea6fc358c-d?mw=800&mh=451",
      "details": {
        "id": "vimeo",
        "message": "use peertube"
      }
    },
    {
      "type": "vimeo",
      "url": "https://fresnel.vimeocdn.com/add/player-stats?beacon=1&session-id=0632d222cfb722f6ffa1bab24cf713736ec19ca51662274103",
      "details": {
        "id": "vimeo",
        "message": "use peertube"
      }
    },
    {
      "type": "vimeo",
      "url": "https://fresnel.vimeocdn.com/add/player-test-impression?beacon=1",
      "details": {
        "id": "vimeo",
        "message": "use peertube"
      }
    },
    {
      "type": "vimeo",
      "url": "https://i.vimeocdn.com/video/1068690231-fac2ffabd03f7ec4fca00ad3bda7d1f788ca36088728005d1242b51ba8c2c708-d?mw=800&mh=451",
      "details": {
        "id": "vimeo",
        "message": "use peertube"
      }
    },
    {
      "type": "vimeo",
      "url": "https://fresnel.vimeocdn.com/add/player-stats?beacon=1&session-id=89535d994f8a35ea1d2c0e940471dcca913ef7a51662274103",
      "details": {
        "id": "vimeo",
        "message": "use peertube"
      }
    },
    {
      "type": "vimeo",
      "url": "https://fresnel.vimeocdn.com/add/player-test-impression?beacon=1",
      "details": {
        "id": "vimeo",
        "message": "use peertube"
      }
    },
    {
      "type": "vimeo",
      "url": "https://i.vimeocdn.com/video/1194006922-0bf7f2d94e08c73c5572adc5c84613b078264d51229fa632f3540478fc399cd4-d?mw=800&mh=451",
      "details": {
        "id": "vimeo",
        "message": "use peertube"
      }
    },
    {
      "type": "vimeo",
      "url": "https://fresnel.vimeocdn.com/add/player-stats?beacon=1&session-id=28fd314fd4923bfba3b463abb7877391c8fb46241662274103",
      "details": {
        "id": "vimeo",
        "message": "use peertube"
      }
    },
    {
      "type": "vimeo",
      "url": "https://fresnel.vimeocdn.com/add/player-test-impression?beacon=1",
      "details": {
        "id": "vimeo",
        "message": "use peertube"
      }
    },
    {
      "type": "vimeo",
      "url": "https://i.vimeocdn.com/video/1259822965-1fb41906639b692901e934675787664da0eb9120b56533d49?mw=800&mh=451",
      "details": {
        "id": "vimeo",
        "message": "use peertube"
      }
    },
    {
      "type": "vimeo",
      "url": "https://fresnel.vimeocdn.com/add/player-stats?beacon=1&session-id=f11dc3f3fb463c5f5143e165124acda6d1875d7d1662274103",
      "details": {
        "id": "vimeo",
        "message": "use peertube"
      }
    },
    {
      "type": "vimeo",
      "url": "https://fresnel.vimeocdn.com/add/player-test-impression?beacon=1",
      "details": {
        "id": "vimeo",
        "message": "use peertube"
      }
    },
    {
      "type": "vimeo",
      "url": "https://i.vimeocdn.com/video/1327083600-79df17abbbd56b8e57f78912b8c23cd84949c84b2a6e0ff9af6e02315fe7e2c9-d?mw=800&mh=451",
      "details": {
        "id": "vimeo",
        "message": "use peertube"
      }
    },
    {
      "type": "vimeo",
      "url": "https://fresnel.vimeocdn.com/add/player-stats?beacon=1&session-id=fa26db60c0d76b018881f8df86e9727b6f5e9bfb1662274104",
      "details": {
        "id": "vimeo",
        "message": "use peertube"
      }
    },
    {
      "type": "vimeo",
      "url": "https://fresnel.vimeocdn.com/add/player-test-impression?beacon=1",
      "details": {
        "id": "vimeo",
        "message": "use peertube"
      }
    },
    {
      "type": "vimeo",
      "url": "https://i.vimeocdn.com/video/1310162640-d203197fe429961d85000b729bffb695af57a92d4e7f3836c?mw=800&mh=451",
      "details": {
        "id": "vimeo",
        "message": "use peertube"
      }
    },
    {
      "type": "vimeo",
      "url": "https://fresnel.vimeocdn.com/add/player-stats?beacon=1&session-id=8d0857f4911afbde55fd9ae056aa31f826354b801662274104",
      "details": {
        "id": "vimeo",
        "message": "use peertube"
      }
    },
    {
      "type": "vimeo",
      "url": "https://fresnel.vimeocdn.com/add/player-test-impression?beacon=1",
      "details": {
        "id": "vimeo",
        "message": "use peertube"
      }
    },
    {
      "type": "vimeo",
      "url": "https://i.vimeocdn.com/video/1329848286-b2d02a1d00f50d5abc2dfaecc0f5963d86e7a89d8bfbaf0a84793bb5aed5c37b-d?mw=800&mh=451",
      "details": {
        "id": "vimeo",
        "message": "use peertube"
      }
    },
    {
      "type": "vimeo",
      "url": "https://fresnel.vimeocdn.com/add/player-stats?beacon=1&session-id=de60bdc000741cb9974a48a14ad918827ef7ee4f1662274104",
      "details": {
        "id": "vimeo",
        "message": "use peertube"
      }
    },
    {
      "type": "vimeo",
      "url": "https://fresnel.vimeocdn.com/add/player-test-impression?beacon=1",
      "details": {
        "id": "vimeo",
        "message": "use peertube"
      }
    },
    {
      "type": "vimeo",
      "url": "https://i.vimeocdn.com/video/1335310154-d53a39032b28983faa5542dff6f665aaa52baafeea9355bb3982a16eee659e6a-d?mw=800&mh=451",
      "details": {
        "id": "vimeo",
        "message": "use peertube"
      }
    },
    {
      "type": "vimeo",
      "url": "https://fresnel.vimeocdn.com/add/player-stats?beacon=1&session-id=fc3a40afd8a1e6ab24293913659b1755cb49a70b1662274104",
      "details": {
        "id": "vimeo",
        "message": "use peertube"
      }
    },
    {
      "type": "vimeo",
      "url": "https://fresnel.vimeocdn.com/add/player-test-impression?beacon=1",
      "details": {
        "id": "vimeo",
        "message": "use peertube"
      }
    },
    {
      "type": "vimeo",
      "url": "https://i.vimeocdn.com/video/1329938929-85eb93d872c31bad2dbb0f73c2cf87dcb286ad37da926b2c4cfe72136f2edafd-d?mw=800&mh=451",
      "details": {
        "id": "vimeo",
        "message": "use peertube"
      }
    },
    {
      "type": "vimeo",
      "url": "https://fresnel.vimeocdn.com/add/player-stats?beacon=1&session-id=9059398a43ead61c5240d3fbe690c3bf1e15f1a11662274104",
      "details": {
        "id": "vimeo",
        "message": "use peertube"
      }
    },
    {
      "type": "vimeo",
      "url": "https://fresnel.vimeocdn.com/add/player-test-impression?beacon=1",
      "details": {
        "id": "vimeo",
        "message": "use peertube"
      }
    },
    {
      "type": "vimeo",
      "url": "https://i.vimeocdn.com/video/1348075437-ea38fd38163c7b66d9c364fff4c97581fa71914a5a4dd2cbd4592404e3afee86-d?mw=800&mh=451",
      "details": {
        "id": "vimeo",
        "message": "use peertube"
      }
    },
    {
      "type": "vimeo",
      "url": "https://fresnel.vimeocdn.com/add/player-stats?beacon=1&session-id=390073e6286eb585cad3a6e244baab21abef7b881662274104",
      "details": {
        "id": "vimeo",
        "message": "use peertube"
      }
    },
    {
      "type": "vimeo",
      "url": "https://f.vimeocdn.com/p/4.9.7/js/module/sentry.js",
      "details": {
        "id": "vimeo",
        "message": "use peertube"
      }
    },
    {
      "type": "vimeo",
      "url": "https://i.vimeocdn.com/portrait/35231741_60x60.jpg",
      "details": {
        "id": "vimeo",
        "message": "use peertube"
      }
    },
    {
      "type": "unknown",
      "url": "https://player.vimeo.com/video/486892019"
    },
    {
      "type": "unknown",
      "url": "https://player.vimeo.com/video/515661695"
    },
    {
      "type": "unknown",
      "url": "https://player.vimeo.com/video/649614883"
    },
    {
      "type": "unknown",
      "url": "https://player.vimeo.com/video/486892019"
    },
    {
      "type": "unknown",
      "url": "https://player.vimeo.com/video/515661695"
    },
    {
      "type": "unknown",
      "url": "https://player.vimeo.com/video/649614883"
    },
    {
      "type": "unknown",
      "url": "https://player.vimeo.com/video/591490868"
    },
    {
      "type": "unknown",
      "url": "https://player.vimeo.com/video/577204331"
    },
    {
      "type": "unknown",
      "url": "https://player.vimeo.com/video/617739562"
    },
    {
      "type": "unknown",
      "url": "https://player.vimeo.com/video/657346945"
    },
    {
      "type": "unknown",
      "url": "https://player.vimeo.com/video/658505731"
    },
    {
      "type": "unknown",
      "url": "https://player.vimeo.com/video/658549972"
    },
    {
      "type": "unknown",
      "url": "https://player.vimeo.com/video/660618173"
    },
    {
      "type": "unknown",
      "url": "https://player.vimeo.com/video/665994111"
    },
    {
      "type": "unknown",
      "url": "https://static.addtoany.com/menu/sm.23.html"
    },
    {
      "type": "vimeo",
      "url": "https://fresnel.vimeocdn.com/add/player-test-impression?beacon=1",
      "details": {
        "id": "vimeo",
        "message": "use peertube"
      }
    },
    {
      "type": "vimeo",
      "url": "https://fresnel.vimeocdn.com/add/player-stats?beacon=1&session-id=00d7f0b20035fedbf69862d5b04d8300850c8c391662274107",
      "details": {
        "id": "vimeo",
        "message": "use peertube"
      }
    },
    {
      "type": "vimeo",
      "url": "https://fresnel.vimeocdn.com/add/player-test-impression?beacon=1",
      "details": {
        "id": "vimeo",
        "message": "use peertube"
      }
    },
    {
      "type": "vimeo",
      "url": "https://fresnel.vimeocdn.com/add/player-stats?beacon=1&session-id=1307db95e0e73c799a7d55415353d7e510a64e161662274107",
      "details": {
        "id": "vimeo",
        "message": "use peertube"
      }
    },
    {
      "type": "vimeo",
      "url": "https://fresnel.vimeocdn.com/add/player-test-impression?beacon=1",
      "details": {
        "id": "vimeo",
        "message": "use peertube"
      }
    },
    {
      "type": "vimeo",
      "url": "https://fresnel.vimeocdn.com/add/player-stats?beacon=1&session-id=ce870e9050b68b1c79cbb640730cbba51a623e3f1662274107",
      "details": {
        "id": "vimeo",
        "message": "use peertube"
      }
    },
    {
      "type": "vimeo",
      "url": "https://fresnel.vimeocdn.com/add/player-test-impression?beacon=1",
      "details": {
        "id": "vimeo",
        "message": "use peertube"
      }
    },
    {
      "type": "vimeo",
      "url": "https://i.vimeocdn.com/video/1194006922-0bf7f2d94e08c73c5572adc5c84613b078264d51229fa632f3540478fc399cd4-d?mw=800&mh=451",
      "details": {
        "id": "vimeo",
        "message": "use peertube"
      }
    },
    {
      "type": "vimeo",
      "url": "https://fresnel.vimeocdn.com/add/player-stats?beacon=1&session-id=ab85753fe90620b67f144bc610b2f26ff3f800661662274107",
      "details": {
        "id": "vimeo",
        "message": "use peertube"
      }
    },
    {
      "type": "vimeo",
      "url": "https://fresnel.vimeocdn.com/add/player-test-impression?beacon=1",
      "details": {
        "id": "vimeo",
        "message": "use peertube"
      }
    },
    {
      "type": "vimeo",
      "url": "https://i.vimeocdn.com/video/1310162640-d203197fe429961d85000b729bffb695af57a92d4e7f3836c?mw=800&mh=451",
      "details": {
        "id": "vimeo",
        "message": "use peertube"
      }
    },
    {
      "type": "vimeo",
      "url": "https://fresnel.vimeocdn.com/add/player-stats?beacon=1&session-id=0a11d8f10b22cf3613cdb45cc077e940db8b69e01662274107",
      "details": {
        "id": "vimeo",
        "message": "use peertube"
      }
    },
    {
      "type": "vimeo",
      "url": "https://i.vimeocdn.com/portrait/35231741_60x60.jpg",
      "details": {
        "id": "vimeo",
        "message": "use peertube"
      }
    },
    {
      "type": "vimeo",
      "url": "https://fresnel.vimeocdn.com/add/player-test-impression?beacon=1",
      "details": {
        "id": "vimeo",
        "message": "use peertube"
      }
    },
    {
      "type": "vimeo",
      "url": "https://i.vimeocdn.com/video/1327083600-79df17abbbd56b8e57f78912b8c23cd84949c84b2a6e0ff9af6e02315fe7e2c9-d?mw=800&mh=451",
      "details": {
        "id": "vimeo",
        "message": "use peertube"
      }
    },
    {
      "type": "vimeo",
      "url": "https://fresnel.vimeocdn.com/add/player-stats?beacon=1&session-id=f20eca19565d0425f3e82079ec20f76081845a3f1662274107",
      "details": {
        "id": "vimeo",
        "message": "use peertube"
      }
    },
    {
      "type": "vimeo",
      "url": "https://fresnel.vimeocdn.com/add/player-test-impression?beacon=1",
      "details": {
        "id": "vimeo",
        "message": "use peertube"
      }
    },
    {
      "type": "vimeo",
      "url": "https://i.vimeocdn.com/video/1329938929-85eb93d872c31bad2dbb0f73c2cf87dcb286ad37da926b2c4cfe72136f2edafd-d?mw=800&mh=451",
      "details": {
        "id": "vimeo",
        "message": "use peertube"
      }
    },
    {
      "type": "vimeo",
      "url": "https://fresnel.vimeocdn.com/add/player-stats?beacon=1&session-id=25e3203ac95f169b062f0b3ffa54af9372d073201662274107",
      "details": {
        "id": "vimeo",
        "message": "use peertube"
      }
    },
    {
      "type": "vimeo",
      "url": "https://fresnel.vimeocdn.com/add/player-test-impression?beacon=1",
      "details": {
        "id": "vimeo",
        "message": "use peertube"
      }
    },
    {
      "type": "vimeo",
      "url": "https://i.vimeocdn.com/video/1329848286-b2d02a1d00f50d5abc2dfaecc0f5963d86e7a89d8bfbaf0a84793bb5aed5c37b-d?mw=800&mh=451",
      "details": {
        "id": "vimeo",
        "message": "use peertube"
      }
    },
    {
      "type": "vimeo",
      "url": "https://fresnel.vimeocdn.com/add/player-stats?beacon=1&session-id=d77aed85bf811bb7f3d362da8537dd9b9015facd1662274107",
      "details": {
        "id": "vimeo",
        "message": "use peertube"
      }
    },
    {
      "type": "vimeo",
      "url": "https://fresnel.vimeocdn.com/add/player-test-impression?beacon=1",
      "details": {
        "id": "vimeo",
        "message": "use peertube"
      }
    },
    {
      "type": "vimeo",
      "url": "https://i.vimeocdn.com/video/1335310154-d53a39032b28983faa5542dff6f665aaa52baafeea9355bb3982a16eee659e6a-d?mw=800&mh=451",
      "details": {
        "id": "vimeo",
        "message": "use peertube"
      }
    },
    {
      "type": "vimeo",
      "url": "https://fresnel.vimeocdn.com/add/player-stats?beacon=1&session-id=fcd2c4464b2d7b2d99b0776b5e3ea1f3a10c07a21662274107",
      "details": {
        "id": "vimeo",
        "message": "use peertube"
      }
    },
    {
      "type": "vimeo",
      "url": "https://fresnel.vimeocdn.com/add/player-test-impression?beacon=1",
      "details": {
        "id": "vimeo",
        "message": "use peertube"
      }
    },
    {
      "type": "vimeo",
      "url": "https://i.vimeocdn.com/video/1259822965-1fb41906639b692901e934675787664da0eb9120b56533d49?mw=800&mh=451",
      "details": {
        "id": "vimeo",
        "message": "use peertube"
      }
    },
    {
      "type": "vimeo",
      "url": "https://fresnel.vimeocdn.com/add/player-stats?beacon=1&session-id=dda93c575acf5cbfa9fbff5ea2ff5c3138319e331662274107",
      "details": {
        "id": "vimeo",
        "message": "use peertube"
      }
    },
    {
      "type": "vimeo",
      "url": "https://fresnel.vimeocdn.com/add/player-test-impression?beacon=1",
      "details": {
        "id": "vimeo",
        "message": "use peertube"
      }
    },
    {
      "type": "vimeo",
      "url": "https://i.vimeocdn.com/video/1348075437-ea38fd38163c7b66d9c364fff4c97581fa71914a5a4dd2cbd4592404e3afee86-d?mw=800&mh=451",
      "details": {
        "id": "vimeo",
        "message": "use peertube"
      }
    },
    {
      "type": "vimeo",
      "url": "https://fresnel.vimeocdn.com/add/player-stats?beacon=1&session-id=9e17e3cd50b92f73713e4271734b30af879d313a1662274107",
      "details": {
        "id": "vimeo",
        "message": "use peertube"
      }
    },
    {
      "type": "unknown",
      "url": "https://tag.aticdn.net/624462/smarttag.js"
    },
    {
      "type": "xiti",
      "url": "https://logs1412.xiti.com/hit.xiti?s=624462&idclient=0905694b-a45f-4bcb-b6a9-bf8451d89eda&ts=1662274125404&vtag=5.29.2&ptag=js&r=800x600x24x24&re=800x600&hl=6x48x45&lng=en-US&idp=0648451066622&jv=0&p=Accueil%20|%20Agence%20nationale%20du%20sport&ref=",
      "details": {
        "id": "xiti",
        "message": "Use hosted Matomo instance"
      }
    }
  ],
  "cookies": [
    {
      "name": "BIGipServerpool-ansr-prod.cegedim.cloud-HTTP",
      "value": "!xbZRiOesgSRaNAZnRzbxqujnleDLVtTr31+svVwSMe/30HGp98YPD+gxHX1i3vXVmkl9ItKeZg7vWGQIvwojE6hYamQ=",
      "domain": "www.agencedusport.fr",
      "path": "/",
      "expires": -1,
      "size": 137,
      "httpOnly": true,
      "secure": true,
      "session": true,
      "sameParty": false,
      "sourceScheme": "Secure",
      "sourcePort": 443
    }
  ],
  "headers": {
    "cache-control": "must-revalidate, no-cache, private",
    "connection": "Keep-Alive",
    "content-encoding": "gzip",
    "content-length": "25878",
    "content-type": "text/html; charset=UTF-8",
    "content-language": "fr",
    "date": "Sun, 04 Sep 2022 06:48:21 GMT",
    "expires": "Sun, 19 Nov 1978 05:00:00 GMT",
    "keep-alive": "timeout=5, max=100",
    "link": "<https://www.agencedusport.fr/>; rel=\"canonical\", <https://www.agencedusport.fr/>; rel=\"shortlink\"",
    "permissions-policy": "interest-cohort=()",
    "set-cookie": "BIGipServerpool-ansr-prod.cegedim.cloud-HTTP=!xbZRiOesgSRaNAZnRzbxqujnleDLVtTr31+svVwSMe/30HGp98YPD+gxHX1i3vXVmkl9ItKeZg7vWGQIvwojE6hYamQ=; path=/; Httponly; Secure",
    "strict-transport-security": "max-age=31536000; includeSubDomains",
    "vary": "Accept-Encoding",
    "x-content-type-options": "nosniff",
    "x-drupal-cache": "HIT",
    "x-drupal-dynamic-cache": "MISS",
    "x-frame-options": "SAMEORIGIN",
    "x-generator": "Drupal 9 (https://www.drupal.org)",
    "x-ua-compatible": "IE=edge"
  },
  "endpoints": [
    {
      "hostname": "www.agencedusport.fr",
      "ip": "185.194.82.230",
      "geoip": {
        "continent": {
          "code": "EU",
          "geoname_id": 6255148,
          "names": {
            "de": "Europa",
            "en": "Europe",
            "es": "Europa",
            "fr": "Europe",
            "ja": "ヨーロッパ",
            "pt-BR": "Europa",
            "ru": "Европа",
            "zh-CN": "欧洲"
          }
        },
        "country": {
          "geoname_id": 3017382,
          "is_in_european_union": true,
          "iso_code": "FR",
          "names": {
            "de": "Frankreich",
            "en": "France",
            "es": "Francia",
            "fr": "France",
            "ja": "フランス共和国",
            "pt-BR": "França",
            "ru": "Франция",
            "zh-CN": "法国"
          }
        },
        "location": {
          "accuracy_radius": 500,
          "latitude": 48.8582,
          "longitude": 2.3387,
          "time_zone": "Europe/Paris"
        },
        "registered_country": {
          "geoname_id": 3017382,
          "is_in_european_union": true,
          "iso_code": "FR",
          "names": {
            "de": "Frankreich",
            "en": "France",
            "es": "Francia",
            "fr": "France",
            "ja": "フランス共和国",
            "pt-BR": "França",
            "ru": "Франция",
            "zh-CN": "法国"
          }
        }
      }
    },
    {
      "hostname": "fonts.googleapis.com",
      "ip": "142.250.113.95",
      "geoip": {
        "continent": {
          "code": "NA",
          "geoname_id": 6255149,
          "names": {
            "de": "Nordamerika",
            "en": "North America",
            "es": "Norteamérica",
            "fr": "Amérique du Nord",
            "ja": "北アメリカ",
            "pt-BR": "América do Norte",
            "ru": "Северная Америка",
            "zh-CN": "北美洲"
          }
        },
        "country": {
          "geoname_id": 6252001,
          "iso_code": "US",
          "names": {
            "de": "Vereinigte Staaten",
            "en": "United States",
            "es": "Estados Unidos",
            "fr": "États Unis",
            "ja": "アメリカ",
            "pt-BR": "EUA",
            "ru": "США",
            "zh-CN": "美国"
          }
        },
        "location": {
          "accuracy_radius": 1000,
          "latitude": 37.751,
          "longitude": -97.822,
          "time_zone": "America/Chicago"
        },
        "registered_country": {
          "geoname_id": 6252001,
          "iso_code": "US",
          "names": {
            "de": "Vereinigte Staaten",
            "en": "United States",
            "es": "Estados Unidos",
            "fr": "États Unis",
            "ja": "アメリカ",
            "pt-BR": "EUA",
            "ru": "США",
            "zh-CN": "美国"
          }
        }
      }
    },
    {
      "hostname": "ajax.googleapis.com",
      "ip": "172.217.1.138",
      "geoip": {
        "continent": {
          "code": "NA",
          "geoname_id": 6255149,
          "names": {
            "de": "Nordamerika",
            "en": "North America",
            "es": "Norteamérica",
            "fr": "Amérique du Nord",
            "ja": "北アメリカ",
            "pt-BR": "América do Norte",
            "ru": "Северная Америка",
            "zh-CN": "北美洲"
          }
        },
        "country": {
          "geoname_id": 6252001,
          "iso_code": "US",
          "names": {
            "de": "Vereinigte Staaten",
            "en": "United States",
            "es": "Estados Unidos",
            "fr": "États Unis",
            "ja": "アメリカ",
            "pt-BR": "EUA",
            "ru": "США",
            "zh-CN": "美国"
          }
        },
        "location": {
          "accuracy_radius": 1000,
          "latitude": 37.751,
          "longitude": -97.822,
          "time_zone": "America/Chicago"
        },
        "registered_country": {
          "geoname_id": 6252001,
          "iso_code": "US",
          "names": {
            "de": "Vereinigte Staaten",
            "en": "United States",
            "es": "Estados Unidos",
            "fr": "États Unis",
            "ja": "アメリカ",
            "pt-BR": "EUA",
            "ru": "США",
            "zh-CN": "美国"
          }
        }
      }
    },
    {
      "hostname": "use.fontawesome.com",
      "ip": "104.21.63.54",
      "geoip": null
    },
    {
      "hostname": "fonts.gstatic.com",
      "ip": "142.251.46.131",
      "geoip": {
        "continent": {
          "code": "NA",
          "geoname_id": 6255149,
          "names": {
            "de": "Nordamerika",
            "en": "North America",
            "es": "Norteamérica",
            "fr": "Amérique du Nord",
            "ja": "北アメリカ",
            "pt-BR": "América do Norte",
            "ru": "Северная Америка",
            "zh-CN": "北美洲"
          }
        },
        "country": {
          "geoname_id": 6252001,
          "iso_code": "US",
          "names": {
            "de": "Vereinigte Staaten",
            "en": "United States",
            "es": "Estados Unidos",
            "fr": "États Unis",
            "ja": "アメリカ",
            "pt-BR": "EUA",
            "ru": "США",
            "zh-CN": "美国"
          }
        },
        "location": {
          "accuracy_radius": 1000,
          "latitude": 37.751,
          "longitude": -97.822,
          "time_zone": "America/Chicago"
        },
        "registered_country": {
          "geoname_id": 6252001,
          "iso_code": "US",
          "names": {
            "de": "Vereinigte Staaten",
            "en": "United States",
            "es": "Estados Unidos",
            "fr": "États Unis",
            "ja": "アメリカ",
            "pt-BR": "EUA",
            "ru": "США",
            "zh-CN": "美国"
          }
        }
      }
    },
    {
      "hostname": "static.addtoany.com",
      "ip": "104.22.71.197",
      "geoip": null
    },
    {
      "hostname": "player.vimeo.com",
      "ip": "162.159.128.61",
      "geoip": null
    },
    {
      "hostname": "i.vimeocdn.com",
      "ip": "146.75.106.109",
      "geoip": {
        "continent": {
          "code": "NA",
          "geoname_id": 6255149,
          "names": {
            "de": "Nordamerika",
            "en": "North America",
            "es": "Norteamérica",
            "fr": "Amérique du Nord",
            "ja": "北アメリカ",
            "pt-BR": "América do Norte",
            "ru": "Северная Америка",
            "zh-CN": "北美洲"
          }
        },
        "country": {
          "geoname_id": 6252001,
          "iso_code": "US",
          "names": {
            "de": "Vereinigte Staaten",
            "en": "United States",
            "es": "Estados Unidos",
            "fr": "États Unis",
            "ja": "アメリカ",
            "pt-BR": "EUA",
            "ru": "США",
            "zh-CN": "美国"
          }
        },
        "location": {
          "accuracy_radius": 1000,
          "latitude": 37.751,
          "longitude": -97.822,
          "time_zone": "America/Chicago"
        },
        "registered_country": {
          "geoname_id": 6252001,
          "iso_code": "US",
          "names": {
            "de": "Vereinigte Staaten",
            "en": "United States",
            "es": "Estados Unidos",
            "fr": "États Unis",
            "ja": "アメリカ",
            "pt-BR": "EUA",
            "ru": "США",
            "zh-CN": "美国"
          }
        }
      }
    },
    {
      "hostname": "f.vimeocdn.com",
      "ip": "146.75.106.109",
      "geoip": {
        "continent": {
          "code": "NA",
          "geoname_id": 6255149,
          "names": {
            "de": "Nordamerika",
            "en": "North America",
            "es": "Norteamérica",
            "fr": "Amérique du Nord",
            "ja": "北アメリカ",
            "pt-BR": "América do Norte",
            "ru": "Северная Америка",
            "zh-CN": "北美洲"
          }
        },
        "country": {
          "geoname_id": 6252001,
          "iso_code": "US",
          "names": {
            "de": "Vereinigte Staaten",
            "en": "United States",
            "es": "Estados Unidos",
            "fr": "États Unis",
            "ja": "アメリカ",
            "pt-BR": "EUA",
            "ru": "США",
            "zh-CN": "美国"
          }
        },
        "location": {
          "accuracy_radius": 1000,
          "latitude": 37.751,
          "longitude": -97.822,
          "time_zone": "America/Chicago"
        },
        "registered_country": {
          "geoname_id": 6252001,
          "iso_code": "US",
          "names": {
            "de": "Vereinigte Staaten",
            "en": "United States",
            "es": "Estados Unidos",
            "fr": "États Unis",
            "ja": "アメリカ",
            "pt-BR": "EUA",
            "ru": "США",
            "zh-CN": "美国"
          }
        }
      }
    },
    {
      "hostname": "vimeo.com",
      "ip": "162.159.138.60",
      "geoip": null
    },
    {
      "hostname": "fresnel.vimeocdn.com",
      "ip": "34.120.202.204",
      "geoip": {
        "city": {
          "geoname_id": 4393217,
          "names": {
            "de": "Kansas City",
            "en": "Kansas City",
            "es": "Kansas City",
            "fr": "Kansas City",
            "ja": "カンザスシティ",
            "pt-BR": "Kansas City",
            "ru": "Канзас-Сити"
          }
        },
        "continent": {
          "code": "NA",
          "geoname_id": 6255149,
          "names": {
            "de": "Nordamerika",
            "en": "North America",
            "es": "Norteamérica",
            "fr": "Amérique du Nord",
            "ja": "北アメリカ",
            "pt-BR": "América do Norte",
            "ru": "Северная Америка",
            "zh-CN": "北美洲"
          }
        },
        "country": {
          "geoname_id": 6252001,
          "iso_code": "US",
          "names": {
            "de": "Vereinigte Staaten",
            "en": "United States",
            "es": "Estados Unidos",
            "fr": "États Unis",
            "ja": "アメリカ",
            "pt-BR": "EUA",
            "ru": "США",
            "zh-CN": "美国"
          }
        },
        "location": {
          "accuracy_radius": 1000,
          "latitude": 39.1027,
          "longitude": -94.5778,
          "metro_code": 616,
          "time_zone": "America/Chicago"
        },
        "postal": {
          "code": "64184"
        },
        "registered_country": {
          "geoname_id": 6252001,
          "iso_code": "US",
          "names": {
            "de": "Vereinigte Staaten",
            "en": "United States",
            "es": "Estados Unidos",
            "fr": "États Unis",
            "ja": "アメリカ",
            "pt-BR": "EUA",
            "ru": "США",
            "zh-CN": "美国"
          }
        },
        "subdivisions": [
          {
            "geoname_id": 4398678,
            "iso_code": "MO",
            "names": {
              "en": "Missouri",
              "es": "Missouri",
              "fr": "Missouri",
              "ja": "ミズーリ州",
              "pt-BR": "Missúri",
              "ru": "Миссури",
              "zh-CN": "密苏里州"
            }
          }
        ]
      }
    },
    {
      "hostname": "tag.aticdn.net",
      "ip": "108.156.211.87",
      "geoip": {
        "continent": {
          "code": "NA",
          "geoname_id": 6255149,
          "names": {
            "de": "Nordamerika",
            "en": "North America",
            "es": "Norteamérica",
            "fr": "Amérique du Nord",
            "ja": "北アメリカ",
            "pt-BR": "América do Norte",
            "ru": "Северная Америка",
            "zh-CN": "北美洲"
          }
        },
        "country": {
          "geoname_id": 6252001,
          "iso_code": "US",
          "names": {
            "de": "Vereinigte Staaten",
            "en": "United States",
            "es": "Estados Unidos",
            "fr": "États Unis",
            "ja": "アメリカ",
            "pt-BR": "EUA",
            "ru": "США",
            "zh-CN": "美国"
          }
        },
        "location": {
          "accuracy_radius": 1000,
          "latitude": 37.751,
          "longitude": -97.822,
          "time_zone": "America/Chicago"
        },
        "registered_country": {
          "geoname_id": 6252001,
          "iso_code": "US",
          "names": {
            "de": "Vereinigte Staaten",
            "en": "United States",
            "es": "Estados Unidos",
            "fr": "États Unis",
            "ja": "アメリカ",
            "pt-BR": "EUA",
            "ru": "США",
            "zh-CN": "美国"
          }
        }
      }
    },
    {
      "hostname": "logs1412.xiti.com",
      "ip": "143.204.161.116",
      "geoip": {
        "continent": {
          "code": "NA",
          "geoname_id": 6255149,
          "names": {
            "de": "Nordamerika",
            "en": "North America",
            "es": "Norteamérica",
            "fr": "Amérique du Nord",
            "ja": "北アメリカ",
            "pt-BR": "América do Norte",
            "ru": "Северная Америка",
            "zh-CN": "北美洲"
          }
        },
        "country": {
          "geoname_id": 6252001,
          "iso_code": "US",
          "names": {
            "de": "Vereinigte Staaten",
            "en": "United States",
            "es": "Estados Unidos",
            "fr": "États Unis",
            "ja": "アメリカ",
            "pt-BR": "EUA",
            "ru": "США",
            "zh-CN": "美国"
          }
        },
        "location": {
          "accuracy_radius": 1000,
          "latitude": 37.751,
          "longitude": -97.822,
          "time_zone": "America/Chicago"
        },
        "registered_country": {
          "geoname_id": 6252001,
          "iso_code": "US",
          "names": {
            "de": "Vereinigte Staaten",
            "en": "United States",
            "es": "Estados Unidos",
            "fr": "États Unis",
            "ja": "アメリカ",
            "pt-BR": "EUA",
            "ru": "США",
            "zh-CN": "美国"
          }
        }
      }
    }
  ]
}
