{"urls":{"https://jeunes.gouv.fr/":{"status":200},"https://jeunes.gouv.fr/Ministere-3406":{"status":302},"https://jeunes.gouv.fr/ministere/":{"status":301},"https://jeunes.gouv.fr/-Ministere-":{"status":200},"https://jeunes.gouv.fr/-Equipe-ministerielle-":{"status":200},"https://jeunes.gouv.fr/-Missions-et-organisation-":{"status":200},"https://jeunes.gouv.fr/Organisation-du-ministere":{"status":302},"https://www.education.gouv.fr/federation-des-centres-sociaux-et-socioculturels-de-france-322772":{"status":200},"https://www.education.gouv.fr/donnees-personnelles-et-cookies-12065":{"status":200},"https://jeunes.gouv.fr/Concours-et-recrutement":{"status":302},"https://jeunes.gouv.fr/-Concours-et-recrutement-416-":{"status":200}},"technologies":[{"slug":"drupal","name":"Drupal","confidence":100,"version":"9","icon":"Drupal.svg","website":"https://drupal.org","cpe":"cpe:/a:drupal:drupal","categories":[{"id":1,"slug":"cms","name":"CMS"}]},{"slug":"spip","name":"SPIP","confidence":100,"version":null,"icon":"spip.svg","website":"http://www.spip.net","cpe":null,"categories":[{"id":1,"slug":"cms","name":"CMS"}]},{"slug":"php","name":"PHP","confidence":100,"version":null,"icon":"PHP.svg","website":"http://php.net","cpe":"cpe:/a:php:php","categories":[{"id":27,"slug":"programming-languages","name":"Programming languages"}]},{"slug":"google-sign-in","name":"Google Sign-in","confidence":100,"version":null,"icon":"Google.svg","website":"https://developers.google.com/identity/sign-in/web","cpe":null,"categories":[{"id":69,"slug":"social-logins","name":"Social logins"}]},{"slug":"youtube","name":"YouTube","confidence":100,"version":null,"icon":"YouTube.png","website":"http://www.youtube.com","cpe":null,"categories":[{"id":14,"slug":"video-players","name":"Video players"}]},{"slug":"bootstrap","name":"Bootstrap","confidence":100,"version":"4.0.3","icon":"Bootstrap.svg","website":"https://getbootstrap.com","cpe":"cpe:/a:getbootstrap:bootstrap","categories":[{"id":66,"slug":"ui-frameworks","name":"UI frameworks"}]},{"slug":"nginx","name":"Nginx","confidence":100,"version":null,"icon":"Nginx.svg","website":"http://nginx.org/en","cpe":"cpe:/a:nginx:nginx","categories":[{"id":22,"slug":"web-servers","name":"Web servers"},{"id":64,"slug":"reverse-proxies","name":"Reverse proxies"}]},{"slug":"twitter","name":"Twitter","confidence":100,"version":null,"icon":"Twitter.svg","website":"http://twitter.com","cpe":null,"categories":[{"id":5,"slug":"widgets","name":"Widgets"}]},{"slug":"facebook","name":"Facebook","confidence":100,"version":null,"icon":"Facebook.svg","website":"http://facebook.com","cpe":null,"categories":[{"id":5,"slug":"widgets","name":"Widgets"}]},{"slug":"addthis","name":"AddThis","confidence":100,"version":null,"icon":"AddThis.svg","website":"http://www.addthis.com","cpe":null,"categories":[{"id":5,"slug":"widgets","name":"Widgets"}]},{"slug":"tagcommander","name":"TagCommander","confidence":100,"version":null,"icon":"tagcommander.png","website":"https://www.commandersact.com/en/solutions/tagcommander/","cpe":null,"categories":[{"id":42,"slug":"tag-managers","name":"Tag managers"}]},{"slug":"modernizr","name":"Modernizr","confidence":100,"version":"3.8.0","icon":"Modernizr.svg","website":"https://modernizr.com","cpe":null,"categories":[{"id":59,"slug":"javascript-libraries","name":"JavaScript libraries"}]},{"slug":"at-internet-analyzer","name":"AT Internet Analyzer","confidence":100,"version":null,"icon":"AT Internet.png","website":"http://atinternet.com/en","cpe":null,"categories":[{"id":10,"slug":"analytics","name":"Analytics"}]},{"slug":"google-plus","name":"Google Plus","confidence":100,"version":null,"icon":"Google Plus.svg","website":"http://plus.google.com","cpe":null,"categories":[{"id":5,"slug":"widgets","name":"Widgets"}]},{"slug":"font-awesome","name":"Font Awesome","confidence":100,"version":null,"icon":"font-awesome.svg","website":"https://fontawesome.com/","cpe":null,"categories":[{"id":17,"slug":"font-scripts","name":"Font scripts"}]},{"slug":"jquery-ui","name":"jQuery UI","confidence":100,"version":"1.12.1","icon":"jQuery UI.svg","website":"http://jqueryui.com","cpe":"cpe:/a:jquery:jquery_ui","categories":[{"id":59,"slug":"javascript-libraries","name":"JavaScript libraries"}]},{"slug":"jquery-migrate","name":"jQuery Migrate","confidence":100,"version":"3.0.1","icon":"jQuery.svg","website":"https://github.com/jquery/jquery-migrate","cpe":null,"categories":[{"id":59,"slug":"javascript-libraries","name":"JavaScript libraries"}]},{"slug":"jquery","name":"jQuery","confidence":100,"version":"3.2.1","icon":"jQuery.svg","website":"https://jquery.com","cpe":"cpe:/a:jquery:jquery","categories":[{"id":59,"slug":"javascript-libraries","name":"JavaScript libraries"}]}]}
